{"primary": ["ABINGTON WARD 07 DISTRICT 01", "POTTSTOWN DISTRICT 02 DIVISION 02", "UPPER MERION DISTRICT BELMONT DIVISION 02", "UPPER MERION DISTRICT BELMONT DIVISION 04", "UPPER MERION DISTRICT CANDLEBROOK DIVISION 01", "UPPER MERION DISTRICT KING DIVISION 01", "UPPER MERION DISTRICT KING DIVISION 02", "UPPER PROVIDENCE DISTRICT TRAPPE", "WEST NORRITON DISTRICT 01 DIVISION 02"], "secondary": ["Abington10-2", "Abington12-2", "Abington13-2", "Abington9-2", "Collegeville2", "Collegeville3", "Douglass1", "Franconia1", "Franconia3", "Franconia4", "Franconia5", "Franconia6", "Franconia7", "Franconia8", "Hatfield1-2", "Hatfield2-1", "Hatfield2-2", "Hatfield3-1", "Hatfield3-2", "Hatfield4-1", "Hatfield4-2", "Hatfield5-1", "Hatfield5-2", "HatfieldBorough", "Horsham1-2", "Horsham1-5", "Horsham2-1", "Horsham2-2", "Horsham4-1", "Horsham4-2", "Horsham4-3", "Lansdale3-1", "Lansdale3-2", "Lansdale3-3", "Limerick2", "Limerick6", "LowerMerion11-2", "LowerMerion12-2", "LowerMerion12-3", "LowerMerion14-3", "LowerMoreland3", "LowerProvidence2-3", "LowerProvidence3-1", "LowerProvidence3-2", "LowerProvidence3-4", "Marlborough", "NewHanover1", "NewHanover2", "Perkiomen1", "Plymouth2-3", "Plymouth3-3", "Pottstown3", "Pottstown5", "Pottstown7-1", "Pottstown7-2", "Skippack1", "Skippack2", "Skippack3", "Towamencin1-3", "Towamencin2-3", "Towamencin3-1", "Towamencin3-3", "UpperDublin3-1", "UpperDublin5-1", "UpperDublin5-2", "UpperDublin5-3", "UpperDublin6-1", "UpperGwynedd1", "UpperGwynedd4", "UpperGwynedd5", "UpperMerionBelmont2", "UpperMerionBelmont4", "UpperMerionCandle1", "UpperMerionKing1", "UpperMerionKing2", "UpperMerionRoberts", "UpperMerionTownCenter", "UpperProvidenceMingo1", "UpperProvidenceMingo2", "UpperProvidenceOaks", "WestNorriton2-2", "WestNorriton3-2", "WestNorriton4-1", "WestNorriton4-2", "WestPottsgrove", "WhitemarshEast1", "WhitemarshEast2", "WhitemarshMiddle1", "WhitemarshMiddle2", "WhitemarshMiddle3", "WhitemarshMiddle4", "WhitemarshMiddle5", "WhitemarshWest1", "WhitemarshWest2", "WhitemarshWest3", "Whitpain1", "Whitpain10", "Whitpain11", "Whitpain12", "Whitpain2", "Whitpain3", "Whitpain4", "Whitpain5", "Whitpain6", "Whitpain7", "Whitpain8", "Whitpain9"], "results": {"PENNSBURG": "Pennsburg", "ROCKLEDGE": "Rockledge", "SALFORD": "Salford", "TELFORD": "Telford", "SCHWENKSVILLE": "Schwenksville", "ABINGTON WARD 01 DISTRICT 01": "Abington1-1", "ABINGTON WARD 01 DISTRICT 03": "Abington1-3", "ABINGTON WARD 02 DISTRICT 02": "Abington2-2", "ABINGTON WARD 03 DISTRICT 01": "Abington3-1", "ABINGTON WARD 03 DISTRICT 03": "Abington3-3", "ABINGTON WARD 04 DISTRICT 02": "Abington4-2", "ABINGTON WARD 05 DISTRICT 02": "Abington5-2", "ABINGTON WARD 06 DISTRICT 02": "Abington6-2", "ABINGTON WARD 07 DISTRICT 02": "Abington7-2", "ABINGTON WARD 08 DISTRICT 01": "Abington8-1", "ABINGTON WARD 09 DISTRICT 01": "Abington9-1", "AMBLER DISTRICT 01": "Ambler1", "AMBLER DISTRICT 03": "Ambler3", "BRIDGEPORT DISTRICT 02": "Bridgeport2", "BRYN ATHYN": "BrynAthyn", "CHELTENHAM DISTRICT 01 DIVISION 02": "Cheltenham1-2", "CHELTENHAM DISTRICT 01 DIVISION 04": "Cheltenham1-4", "CHELTENHAM DISTRICT 02 DIVISION 02": "Cheltenham2-2", "CHELTENHAM DISTRICT 02 DIVISION 04": "Cheltenham2-4", "CHELTENHAM DISTRICT 03 DIVISION 02": "Cheltenham3-2", "CHELTENHAM DISTRICT 03 DIVISION 04": "Cheltenham3-4", "CHELTENHAM DISTRICT 04 DIVISION 02": "Cheltenham4-2", "CHELTENHAM DISTRICT 04 DIVISION 04": "Cheltenham4-4", "CHELTENHAM DISTRICT 05 DIVISION 02": "Cheltenham5-2", "CHELTENHAM DISTRICT 05 DIVISION 04": "Cheltenham5-4", "CHELTENHAM DISTRICT 06 DIVISION 02": "Cheltenham6-2", "CHELTENHAM DISTRICT 07 DIVISION 01": "Cheltenham7-1", "CHELTENHAM DISTRICT 07 DIVISION 03": "Cheltenham7-3", "CONSHOHOCKEN DISTRICT 01": "Conshohocken1", "CONSHOHOCKEN DISTRICT 03": "Conshohocken3", "CONSHOHOCKEN DISTRICT 05": "Conshohocken5", "CONSHOHOCKEN DISTRICT 07": "Conshohocken7", "DOUGLASS DISTRICT 03": "Douglass3", "EAST GREENVILLE": "EastGreenville", "EAST NORRITON DISTRICT 01 DIVISION 02": "EastNorriton1-2", "EAST NORRITON DISTRICT 01 DIVISION 04": "EastNorriton1-4", "EAST NORRITON DISTRICT 02 DIVISION 02": "EastNorriton2-2", "EAST NORRITON DISTRICT 02 DIVISION 04": "EastNorriton2-4", "GREEN LANE": "GreenLane", "HATBORO DISTRICT NORTH DIVISION 02": "HatboroNorth2", "HATBORO DISTRICT SOUTH DIVISION 02": "HatboroSouth2", "HORSHAM DISTRICT 01 DIVISION 01": "Horsham1-1", "HORSHAM DISTRICT 01 DIVISION 04": "Horsham1-4", "HORSHAM DISTRICT 02 DIVISION 04": "Horsham2-4", "HORSHAM DISTRICT 03 DIVISION 02": "Horsham3-2", "HORSHAM DISTRICT 03 DIVISION 04": "Horsham3-4", "HORSHAM DISTRICT 04 DIVISION 04": "Horsham4-4", "JENKINTOWN DISTRICT 02": "Jenkintown2", "JENKINTOWN DISTRICT 04": "Jenkintown4", "LANSDALE DISTRICT 01 DIVISION 02": "Lansdale1-2", "LANSDALE DISTRICT 02 DIVISION 01": "Lansdale2-1", "LANSDALE DISTRICT 02 DIVISION 03": "Lansdale2-3", "LIMERICK DISTRICT 03": "Limerick3", "LIMERICK DISTRICT 05": "Limerick5", "LOWER FREDERICK DISTRICT 02": "LowerFrederick2", "LOWER GWYNEDD DISTRICT 01 DIVISION 02": "LowerGwynedd1-2", "LOWER GWYNEDD DISTRICT 01 DIVISION 04": "LowerGwynedd1-4", "LOWER GWYNEDD DISTRICT 02 DIVISION 02": "LowerGwynedd2-2", "LOWER MERION WARD 01 PRECINCT 02": "LowerMerion1-2", "LOWER MERION WARD 02 PRECINCT 01": "LowerMerion2-1", "LOWER MERION WARD 02 PRECINCT 03": "LowerMerion2-3", "LOWER MERION WARD 03 PRECINCT 02": "LowerMerion3-2", "LOWER MERION WARD 04 PRECINCT 01": "LowerMerion4-1", "LOWER MERION WARD 04 PRECINCT 03": "LowerMerion4-3", "LOWER MERION WARD 05 PRECINCT 02": "LowerMerion5-2", "LOWER MERION WARD 06 PRECINCT 01": "LowerMerion6-1", "LOWER MERION WARD 06 PRECINCT 03": "LowerMerion6-3", "LOWER MERION WARD 07 PRECINCT 02": "LowerMerion7-2", "LOWER MERION WARD 08 PRECINCT 01": "LowerMerion8-1", "LOWER MERION WARD 08 PRECINCT 03": "LowerMerion8-3", "LOWER MERION WARD 09 PRECINCT 01": "LowerMerion9-1", "LOWER MERION WARD 09 PRECINCT 03": "LowerMerion9-3", "LOWER MORELAND DISTRICT 01": "LowerMoreland1", "LOWER MORELAND DISTRICT 04 PRECINCT 01": "LowerMoreland4-1", "LOWER MORELAND DISTRICT 05": "LowerMoreland5", "LOWER POTTSGROVE DISTRICT 01": "LowerPottsgrove1", "LOWER POTTSGROVE DISTRICT 03": "LowerPottsgrove3", "LOWER PROVIDENCE DISTRICT 01 DIVISION 01": "LowerProvidence1-1", "LOWER PROVIDENCE DISTRICT 02 DIVISION 01": "LowerProvidence2-1", "LOWER PROVIDENCE DISTRICT 02 DIVISION 04": "LowerProvidence2-4", "LOWER SALFORD DISTRICT 01": "LowerSalford1", "LOWER SALFORD DISTRICT 03": "LowerSalford3", "LOWER SALFORD DISTRICT 05": "LowerSalford5", "MONTGOMERY DISTRICT 01": "Montgomery1", "MONTGOMERY DISTRICT 03": "Montgomery3", "MONTGOMERY DISTRICT 05": "Montgomery5", "MONTGOMERY DISTRICT 07": "Montgomery7", "NARBERTH DISTRICT 01": "Narberth1", "NARBERTH DISTRICT 03": "Narberth3", "NORRISTOWN DISTRICT 01 DIVISION 01": "Norristown1-1", "NORRISTOWN DISTRICT 01 DIVISION 03": "Norristown1-3", "NORRISTOWN DISTRICT 02 DIVISION 02": "Norristown2-2", "NORRISTOWN DISTRICT 03 DIVISION 01": "Norristown3-1", "NORRISTOWN DISTRICT 03 DIVISION 03": "Norristown3-3", "NORRISTOWN DISTRICT 04 DIVISION 02": "Norristown4-2", "NORTH WALES DISTRICT 01": "NorthWales1", "NORTH WALES DISTRICT 03": "NorthWales3", "PLYMOUTH DISTRICT 01 DIVISION 01": "Plymouth1-1", "PLYMOUTH DISTRICT 02 DIVISION 01": "Plymouth2-1", "PLYMOUTH DISTRICT 03 DIVISION 01": "Plymouth3-1", "PLYMOUTH DISTRICT 04 DIVISION 01": "Plymouth4-1", "POTTSTOWN DISTRICT 01 DIVISION 01": "Pottstown1-1", "POTTSTOWN DISTRICT 02 DIVISION 01": "Pottstown2-1", "POTTSTOWN DISTRICT 04": "Pottstown4", "POTTSTOWN DISTRICT 06": "Pottstown6", "ROYERSFORD DISTRICT 01": "Royersford1", "SOUDERTON DISTRICT 01": "Souderton1", "SOUDERTON DISTRICT 03": "Souderton3", "SPRINGFIELD DISTRICT 01 DIVISION 02": "Springfield1-2", "SPRINGFIELD DISTRICT 02 DIVISION 02": "Springfield2-2", "SPRINGFIELD DISTRICT 03 DIVISION 01": "Springfield3-1", "SPRINGFIELD DISTRICT 04 DIVISION 01": "Springfield4-1", "SPRINGFIELD DISTRICT 05 DIVISION 01": "Springfield5-1", "SPRINGFIELD DISTRICT 06 DIVISION 01": "Springfield6-1", "SPRINGFIELD DISTRICT 07 DIVISION 01": "Springfield7-1", "TOWAMENCIN DISTRICT 01 DIVISION 01": "Towamencin1-1", "TOWAMENCIN DISTRICT 02 DIVISION 01": "Towamencin2-1", "TOWAMENCIN DISTRICT 03 DIVISION 02": "Towamencin3-2", "UPPER DUBLIN DISTRICT 01 DIVISION 01": "UpperDublin1-1", "UPPER DUBLIN DISTRICT 01 DIVISION 03": "UpperDublin1-3", "UPPER DUBLIN DISTRICT 02 DIVISION 02": "UpperDublin2-2", "UPPER DUBLIN DISTRICT 03 DIVISION 02": "UpperDublin3-2", "UPPER DUBLIN DISTRICT 04 DIVISION 02": "UpperDublin4-2", "UPPER DUBLIN DISTRICT 06 DIVISION 02": "UpperDublin6-2", "UPPER DUBLIN DISTRICT 07 DIVISION 02": "UpperDublin7-2", "UPPER FREDERICK": "UpperFrederick", "UPPER GWYNEDD DISTRICT 03": "UpperGwynedd3", "UPPER GWYNEDD DISTRICT 07": "UpperGwynedd7", "UPPER HANOVER DISTRICT 02": "UpperHanover2", "UPPER MERION DISTRICT GULPH DIVISION 01": "UpperMerionGulph1", "UPPER MERION DISTRICT SWEDELAND": "UpperMerionSwedeland", "UPPER MORELAND DISTRICT 01 DIVISION 01": "UpperMoreland1-1", "UPPER MORELAND DISTRICT 02 DIVISION 01": "UpperMoreland2-1", "UPPER MORELAND DISTRICT 03 DIVISION 01": "UpperMoreland3-1", "UPPER MORELAND DISTRICT 04 DIVISION 01": "UpperMoreland4-1", "UPPER MORELAND DISTRICT 05 DIVISION 01": "UpperMoreland5-1", "UPPER MORELAND DISTRICT 06 DIVISION 01": "UpperMoreland6-1", "UPPER MORELAND DISTRICT 07 DIVISION 01": "UpperMoreland7-1", "UPPER POTTSGROVE": "UpperPottsgrove", "UPPER PROVIDENCE DISTRICT OAKS": "UpperProvidenceTrappe", "UPPER SALFORD": "UpperSalford", "WEST NORRITON DISTRICT 01 DIVISION 01": "WestNorriton1-1", "WEST NORRITON DISTRICT 02 DIVISION 01": "WestNorriton2-1", "WORCESTER DISTRICT EAST DISTRICT 02": "WorcesterEast2", "WORCESTER DISTRICT WEST": "WorcesterWest", "ABINGTON WARD 01 DISTRICT 02": "Abington1-2", "ABINGTON WARD 02 DISTRICT 03": "Abington2-3", "ABINGTON WARD 04 DISTRICT 01": "Abington4-1", "ABINGTON WARD 06 DISTRICT 01": "Abington6-1", "ABINGTON WARD 07 DISTRICT 03": "Abington7-3", "ABINGTON WARD 10 DISTRICT 01": "Abington10-1", "ABINGTON WARD 10 DISTRICT 03": "Abington10-3", "ABINGTON WARD 11 DISTRICT 03": "Abington11-3", "ABINGTON WARD 13 DISTRICT 01": "Abington13-1", "ABINGTON WARD 14 DISTRICT 01": "Abington14-1", "ABINGTON WARD 15 DISTRICT 01": "Abington15-1", "AMBLER DISTRICT 02": "Ambler2", "BRIDGEPORT DISTRICT 03": "Bridgeport3", "CHELTENHAM DISTRICT 01 DIVISION 03": "Cheltenham1-3", "CHELTENHAM DISTRICT 02 DIVISION 03": "Cheltenham2-3", "CHELTENHAM DISTRICT 03 DIVISION 03": "Cheltenham3-3", "CHELTENHAM DISTRICT 04 DIVISION 03": "Cheltenham4-3", "CHELTENHAM DISTRICT 05 DIVISION 03": "Cheltenham5-3", "CHELTENHAM DISTRICT 06 DIVISION 03": "Cheltenham6-3", "COLLEGEVILLE DISTRICT 01": "Collegeville1", "CONSHOHOCKEN DISTRICT 04": "Conshohocken4", "DOUGLASS DISTRICT 02": "Douglass2", "EAST NORRITON DISTRICT 01 DIVISION 01": "EastNorriton1-1", "EAST NORRITON DISTRICT 02 DIVISION 01": "EastNorriton2-1", "HATBORO DISTRICT NORTH DIVISION 01": "HatboroNorth1", "HATFIELD": "Hatfield1-1", "HORSHAM DISTRICT 02 DIVISION 03": "Horsham2-3", "HORSHAM DISTRICT 03 DIVISION 03": "Horsham3-3", "JENKINTOWN DISTRICT 01": "Jenkintown1", "LANSDALE DISTRICT 01 DIVISION 01": "Lansdale1-1", "LANSDALE DISTRICT 02 DIVISION 02": "Lansdale2-2", "LIMERICK DISTRICT 04": "Limerick4", "LOWER GWYNEDD DISTRICT 01 DIVISION 01": "LowerGwynedd1-1", "LOWER GWYNEDD DISTRICT 02 DIVISION 01": "LowerGwynedd2-1", "LOWER MERION WARD 01 PRECINCT 03": "LowerMerion1-3", "LOWER MERION WARD 03 PRECINCT 01": "LowerMerion3-1", "LOWER MERION WARD 04 PRECINCT 02": "LowerMerion4-2", "LOWER MERION WARD 05 PRECINCT 03": "LowerMerion5-3", "LOWER MERION WARD 07 PRECINCT 01": "LowerMerion7-1", "LOWER MERION WARD 08 PRECINCT 02": "LowerMerion8-2", "LOWER MERION WARD 09 PRECINCT 02": "LowerMerion9-2", "LOWER MERION WARD 10 PRECINCT 02": "LowerMerion10-2", "LOWER MERION WARD 11 PRECINCT 01": "LowerMerion11-1", "LOWER MERION WARD 12 PRECINCT 01": "LowerMerion12-1", "LOWER MERION WARD 13 PRECINCT 03": "LowerMerion13-3", "LOWER MORELAND DISTRICT 02": "LowerMoreland2", "LOWER MORELAND DISTRICT 06": "LowerMoreland6", "LOWER POTTSGROVE DISTRICT 04": "LowerPottsgrove4", "LOWER PROVIDENCE DISTRICT 02 DIVISION 02": "LowerProvidence2-2", "LOWER SALFORD DISTRICT 02": "LowerSalford2", "LOWER SALFORD DISTRICT 06": "LowerSalford6", "MONTGOMERY DISTRICT 04": "Montgomery4", "MONTGOMERY DISTRICT 08": "Montgomery8", "NORRISTOWN DISTRICT 01 DIVISION 02": "Norristown1-2", "NORRISTOWN DISTRICT 02 DIVISION 03": "Norristown2-3", "NORRISTOWN DISTRICT 04 DIVISION 01": "Norristown4-1", "NORTH WALES DISTRICT 02": "NorthWales2", "PLYMOUTH DISTRICT 01 DIVISION 02": "Plymouth1-2", "PLYMOUTH DISTRICT 03 DIVISION 02": "Plymouth3-2", "POTTSTOWN DISTRICT 01 DIVISION 02": "Pottstown1-2", "POTTSTOWN DISTRICT 05": "Pottstown2-2", "ROYERSFORD DISTRICT 02": "Royersford2", "SPRINGFIELD DISTRICT 01 DIVISION 01": "Springfield1-1", "SPRINGFIELD DISTRICT 02 DIVISION 03": "Springfield2-3", "SPRINGFIELD DISTRICT 04 DIVISION 02": "Springfield4-2", "SPRINGFIELD DISTRICT 06 DIVISION 02": "Springfield6-2", "TOWAMENCIN DISTRICT 01 DIVISION 02": "Towamencin1-2", "TRAPPE": "TrappeBoro", "UPPER DUBLIN DISTRICT 02 DIVISION 01": "UpperDublin2-1", "UPPER DUBLIN DISTRICT 04 DIVISION 01": "UpperDublin4-1", "UPPER DUBLIN DISTRICT 07 DIVISION 01": "UpperDublin7-1", "UPPER GWYNEDD DISTRICT 02": "UpperGwynedd2", "UPPER HANOVER DISTRICT 01": "UpperHanover1", "UPPER MERION DISTRICT GULPH DIVISION 02": "UpperMerionGulph2", "UPPER MERION DISTRICT SWEDESBURG": "UpperMerionSwedesburg", "UPPER MORELAND DISTRICT 02 DIVISION 02": "UpperMoreland2-2", "UPPER MORELAND DISTRICT 04 DIVISION 02": "UpperMoreland4-2", "UPPER MORELAND DISTRICT 06 DIVISION 02": "UpperMoreland6-2", "WEST CONSHOHOCKEN": "WestConshohocken", "WORCESTER DISTRICT EAST DISTRICT 01": "WorcesterEast1", "ABINGTON WARD 02 DISTRICT 01": "Abington2-1", "ABINGTON WARD 05 DISTRICT 01": "Abington5-1", "ABINGTON WARD 08 DISTRICT 02": "Abington8-2", "ABINGTON WARD 11 DISTRICT 01": "Abington11-1", "ABINGTON WARD 12 DISTRICT 01": "Abington12-1", "ABINGTON WARD 13 DISTRICT 03": "Abington13-3", "ABINGTON WARD 15 DISTRICT 02": "Abington15-2", "CHELTENHAM DISTRICT 01 DIVISION 01": "Cheltenham1-1", "CHELTENHAM DISTRICT 03 DIVISION 01": "Cheltenham3-1", "CHELTENHAM DISTRICT 05 DIVISION 01": "Cheltenham5-1", "CHELTENHAM DISTRICT 07 DIVISION 02": "Cheltenham7-2", "CONSHOHOCKEN DISTRICT 06": "Conshohocken6", "EAST NORRITON DISTRICT 01 DIVISION 03": "EastNorriton1-3", "FRANCONIA PRECINCT 02 (CD 04)": "Franconia2", "HORSHAM DISTRICT 01 DIVISION 03": "Horsham1-3", "HORSHAM DISTRICT 03 DIVISION 05": "Horsham3-5", "LANSDALE DISTRICT 01 DIVISION 03": "Lansdale1-3", "LOWER FREDERICK DISTRICT 01": "LowerFrederick1", "LOWER MERION WARD 01 PRECINCT 01": "LowerMerion1-1", "LOWER MERION WARD 03 PRECINCT 03": "LowerMerion3-3", "LOWER MERION WARD 06 PRECINCT 02": "LowerMerion6-2", "LOWER MERION WARD 08 PRECINCT 04": "LowerMerion8-4", "LOWER MERION WARD 10 PRECINCT 03": "LowerMerion10-3", "LOWER MERION WARD 13 PRECINCT 01": "LowerMerion13-1", "LOWER MERION WARD 14 PRECINCT 01": "LowerMerion14-1", "LOWER MORELAND DISTRICT 04 PRECINCT 02": "LowerMoreland4-2", "LOWER PROVIDENCE DISTRICT 01 DIVISION 02": "LowerProvidence1-2", "LOWER SALFORD DISTRICT 04": "LowerSalford4", "MONTGOMERY DISTRICT 06": "Montgomery6", "NORRISTOWN DISTRICT 02 DIVISION 01": "Norristown2-1", "NORRISTOWN DISTRICT 04 DIVISION 03": "Norristown4-3", "PLYMOUTH DISTRICT 02 DIVISION 02": "Plymouth2-2", "RED HILL": "RedHill", "SPRINGFIELD DISTRICT 02 DIVISION 01": "Springfield2-1", "SPRINGFIELD DISTRICT 05 DIVISION 02": "Springfield5-2", "TOWAMENCIN DISTRICT 02 DIVISION 02": "Towamencin2-2", "UPPER DUBLIN DISTRICT 02 DIVISION 03": "UpperDublin2-3", "UPPER DUBLIN DISTRICT 07 DIVISION 03": "UpperDublin7-3", "UPPER HANOVER DISTRICT 03": "UpperHanover3", "UPPER MORELAND DISTRICT 01 DIVISION 02": "UpperMoreland1-2", "UPPER MORELAND DISTRICT 05 DIVISION 02": "UpperMoreland5-2", "WORCESTER DISTRICT EAST DISTRICT 03": "WorcesterEast3", "ABINGTON WARD 03 DISTRICT 02": "Abington3-2", "ABINGTON WARD 10 DISTRICT 02": "Abington7-1", "ABINGTON WARD 12 DISTRICT 03": "Abington12-3", "BRIDGEPORT DISTRICT 01": "Bridgeport1", "CHELTENHAM DISTRICT 04 DIVISION 01": "Cheltenham4-1", "CONSHOHOCKEN DISTRICT 02": "Conshohocken2", "EAST NORRITON DISTRICT 02 DIVISION 03": "EastNorriton2-3", "HORSHAM DISTRICT 03 DIVISION 01": "Horsham3-1", "LIMERICK DISTRICT 01": "Limerick1", "LOWER MERION WARD 02 PRECINCT 02": "LowerMerion2-2", "LOWER MERION WARD 07 PRECINCT 03": "LowerMerion7-3", "LOWER MERION WARD 11 PRECINCT 03": "LowerMerion11-3", "LOWER MERION WARD 14 PRECINCT 02": "LowerMerion14-2", "LOWER PROVIDENCE DISTRICT 03 DISTRICT 03": "LowerProvidence3-3", "NARBERTH DISTRICT 02": "Narberth2", "NORRISTOWN DISTRICT 03 DIVISION 02": "Norristown3-2", "PLYMOUTH DISTRICT 04 DIVISION 02": "Plymouth4-2", "SOUDERTON DISTRICT 02": "Souderton2", "SPRINGFIELD DISTRICT 07 DIVISION 02": "Springfield7-2", "UPPER DUBLIN DISTRICT 04 DIVISION 03": "UpperDublin4-3", "UPPER MORELAND DISTRICT 03 DIVISION 02": "UpperMoreland3-2", "ABINGTON WARD 11 DISTRICT 02": "Abington11-2", "CHELTENHAM DISTRICT 02 DIVISION 01": "Cheltenham2-1", "DOUGLASS DISTRICT 04": "Douglass4", "JENKINTOWN DISTRICT 03": "Jenkintown3", "LOWER MERION WARD 05 PRECINCT 01": "LowerMerion5-1", "LOWER MERION WARD 13 PRECINCT 02": "LowerMerion13-2", "MONTGOMERY DISTRICT 02": "Montgomery2", "PERKIOMEN DISTRICT 02": "Perkiomen2", "SPRINGFIELD DISTRICT 03 DIVISION 02": "Springfield3-2", "UPPER GWYNEDD DISTRICT 06": "UpperGwynedd6", "UPPER MORELAND DISTRICT 07 DIVISION 02": "UpperMoreland7-2", "ABINGTON WARD 14 DISTRICT 02": "Abington14-2", "HATBORO DISTRICT SOUTH DIVISION 01": "HatboroSouth1", "LOWER MERION WARD 10 PRECINCT 01": "LowerMerion10-1", "NEW HANOVER DISTRICT 01": "WestNorriton3-1", "UPPER DUBLIN DISTRICT 01 DIVISION 02": "UpperDublin1-2", "CHELTENHAM DISTRICT 06 DIVISION 01": "Cheltenham6-1", "LOWER POTTSGROVE DISTRICT 02": "LowerPottsgrove2", "LOWER GWYNEDD DISTRICT 01 DIVISION 03": "LowerGwynedd1-3", "NEW HANOVER DISTRICT 03": "NewHanover3", "UPPER PROVIDENCE DISTRICT MONT CLARE": "UpperProvidenceMontClare", "UPPER MERION DISTRICT BELMONT DIVISION 01": "UpperMerionBelmont1", "UPPER MERION DISTRICT BELMONT DIVISION 03": "UpperMerionBelmont3", "UPPER MERION DISTRICT BELMONT DIVISION 05": "UpperMerionBelmont5", "UPPER MERION DISTRICT CANDLEBROOK DIVISION 02": "UpperMerionCandle2"}}